sigma/backends/databricks/__init__.py
sigma/backends/databricks/databricks.py
sigma/pipelines/databricks/__init__.py
sigma/pipelines/databricks/snake_case.py
pysigma_backend_databricks-0.1.5.dist-info/METADATA
pysigma_backend_databricks-0.1.5.dist-info/WHEEL
pysigma_backend_databricks-0.1.5.dist-info/licenses/LICENSE
pysigma_backend_databricks-0.1.5.dist-info/RECORD
