Metadata-Version: 2.4
Name: pySigma-backend-databricks
Version: 0.1.5
Summary: pySigma backend for Apache Spark/Databricks
License-Expression: Apache-2.0
License-File: LICENSE
Keywords: cybersecurity,apache spark,spark,sigma,databricks
Author: Alex Ott
Author-email: alexott@gmail.com
Requires-Python: >=3.10,<=3.14
Classifier: Programming Language :: Python :: 3
Classifier: Programming Language :: Python :: 3.10
Classifier: Programming Language :: Python :: 3.11
Classifier: Programming Language :: Python :: 3.12
Classifier: Programming Language :: Python :: 3.13
Classifier: Programming Language :: Python :: 3.14
Requires-Dist: inflection (>=0.5.1,<0.6.0)
Requires-Dist: pysigma (>=1.0.2,<2.0.0)
Project-URL: Homepage, https://github.com/alexott/cyber-spark-data-connectors
Project-URL: Issues, https://github.com/alexott/cyber-spark-data-connectors/issues
